autora/theorist/darts/__init__.py
autora/theorist/darts/architect.py
autora/theorist/darts/dataset.py
autora/theorist/darts/fan_out.py
autora/theorist/darts/model_search.py
autora/theorist/darts/operations.py
autora/theorist/darts/regressor.py
autora/theorist/darts/utils.py
autora/theorist/darts/visualize.py
autora_darts-3.0.0a2.dist-info/LICENSE.md
autora_darts-3.0.0a2.dist-info/METADATA
autora_darts-3.0.0a2.dist-info/WHEEL
autora_darts-3.0.0a2.dist-info/RECORD
