Metadata-Version: 2.1
Name: autora-darts
Version: 3.0.0a2
Summary: 
Author: Sebastian Musslick
Author-email: sebastian_musslick@brown.edu
Requires-Python: >=3.8.10,<3.11
Classifier: Programming Language :: Python :: 3
Classifier: Programming Language :: Python :: 3.9
Classifier: Programming Language :: Python :: 3.10
Requires-Dist: autora-core (==3.0.0a2)
Requires-Dist: graphviz (>=0.14.1,<0.21.0)
Requires-Dist: torch (==2.0.0)
Requires-Dist: tqdm (>=4.64.0,<5.0.0)
